MANIFEST.in
README.rst
setup.py
tox.ini
pyramid_restful_toolkit/__init__.py
pyramid_restful_toolkit/__init__.pyc
pyramid_restful_toolkit/api_doc.pyc
pyramid_restful_toolkit/error_handlers.py
pyramid_restful_toolkit/error_handlers.pyc
pyramid_restful_toolkit/renderer.py
pyramid_restful_toolkit/renderer.pyc
pyramid_restful_toolkit/tweens.py
pyramid_restful_toolkit/tweens.pyc
pyramid_restful_toolkit/utils.py
pyramid_restful_toolkit/utils.pyc
pyramid_restful_toolkit.egg-info/PKG-INFO
pyramid_restful_toolkit.egg-info/SOURCES.txt
pyramid_restful_toolkit.egg-info/dependency_links.txt
pyramid_restful_toolkit.egg-info/not-zip-safe
pyramid_restful_toolkit.egg-info/requires.txt
pyramid_restful_toolkit.egg-info/top_level.txt
pyramid_restful_toolkit/__pycache__/__init__.cpython-34.pyc
pyramid_restful_toolkit/__pycache__/api_doc.cpython-34.pyc
pyramid_restful_toolkit/__pycache__/error_handlers.cpython-34.pyc
pyramid_restful_toolkit/__pycache__/renderer.cpython-34.pyc
pyramid_restful_toolkit/__pycache__/tweens.cpython-34.pyc
pyramid_restful_toolkit/__pycache__/utils.cpython-34.pyc
pyramid_restful_toolkit/tests/__init__.py
pyramid_restful_toolkit/tests/__init__.pyc
pyramid_restful_toolkit/tests/test_error_handlers.py
pyramid_restful_toolkit/tests/__pycache__/__init__.cpython-34.pyc
pyramid_restful_toolkit/tests/__pycache__/test_error_handlers.cpython-27-PYTEST.pyc
pyramid_restful_toolkit/tests/__pycache__/test_error_handlers.cpython-34-PYTEST.pyc