Metadata-Version: 1.1
Name: pyramid-restful-toolkit
Version: 1.1.1
Summary: Some toolkit for RESTful API development in Pyramid.
Home-page: https://github.com/tarzanjw/pyramid_restful_toolkit
Author: Học .T Đỗ
Author-email: hoc3010@gmail.com
License: UNKNOWN
Keywords: web wsgi bfg pylons pyramid restful toolkit
Platform: UNKNOWN
Classifier: Programming Language :: Python
Classifier: Framework :: Pyramid
Classifier: Topic :: Internet :: WWW/HTTP
Classifier: Topic :: Internet :: WWW/HTTP :: WSGI :: Application
